_softposit.cpython-36m-x86_64-linux-gnu.so
softposit.py
softposit-0.3.4.4.data/data/LICENSE
softposit-0.3.4.4.dist-info/LICENSE.txt
softposit-0.3.4.4.dist-info/METADATA
softposit-0.3.4.4.dist-info/RECORD
softposit-0.3.4.4.dist-info/WHEEL
softposit-0.3.4.4.dist-info/top_level.txt
