Metadata-Version: 2.1
Name: softposit
Version: 0.3.4.4
Summary: SoftPosit Python Package
Home-page: https://gitlab.com/cerlane/SoftPosit-Python
Author: Siew Hoon LEONG (Cerlane)
Author-email: cerlane@posithub.org
License: UNKNOWN
Platform: UNKNOWN
Classifier: Programming Language :: Python :: 3
Classifier: License :: OSI Approved :: MIT License
Classifier: Operating System :: OS Independent
